README.md
setup.py
TakeTheTime.egg-info/PKG-INFO
TakeTheTime.egg-info/SOURCES.txt
TakeTheTime.egg-info/dependency_links.txt
TakeTheTime.egg-info/requires.txt
TakeTheTime.egg-info/top_level.txt
takethetime/__init__.py
takethetime/takethetime.py