Metadata-Version: 1.0
Name: TakeTheTime
Version: 0.3.1
Summary: Take The Time, a time-taking library for Python
Home-page: https://github.com/ErikBjare/TakeTheTime
Author: Erik Bjäreholt
Author-email: erik@bjareho.lt
License: UNKNOWN
Platform: UNKNOWN
